<?xml version="1.0" encoding="UTF-8" standalone="no" ?>
<GDTF DataVersion="1.1">

  <FixtureType CanHaveChildren="Yes" Description="" FixtureTypeID="84675947-553E-11EB-A40F-2E4D546E0304" LongName="" Manufacturer="Custom" Name="Martin MAC 700 Profile" RefFT="" ShortName="Martin MAC 700 Profile" Thumbnail="">
    <AttributeDefinitions>
      <ActivationGroups/>
      <FeatureGroups>
        <FeatureGroup Name="Dimmer" Pretty="Dimmer">
          <Feature Name="Dimmer"/>
        </FeatureGroup>
      </FeatureGroups>
      <Attributes>
        <Attribute Feature="Dimmer.Dimmer" Name="Dimmer" PhysicalUnit="None" Pretty="Dim"/>
      </Attributes>
    </AttributeDefinitions>
    <Wheels>
      <Wheel Name="Gobo Wheel 1">
        <Slot Color="0.312730,0.329020,100.000000" MediaFileName="Blank gobo" Name=""/>
        <Slot Color="0.312730,0.329020,100.000000" MediaFileName="MT Spiral" Name="MT Spiral.dds"/>
        <Slot Color="0.312730,0.329020,100.000000" MediaFileName="MT Radial Circles" Name="MT Radial Circles.dds"/>
        <Slot Color="0.312730,0.329020,100.000000" MediaFileName="MT Fused Red-Yellow" Name="MT Fused Red-Yellow.dds"/>
        <Slot Color="0.312730,0.329020,100.000000" MediaFileName="MT Milkyway" Name="MT Milkyway.dds"/>
        <Slot Color="0.312730,0.329020,100.000000" MediaFileName="MT Water" Name="MT Water.dds"/>
        <Slot Color="0.312730,0.329020,100.000000" MediaFileName="MT Flames 6" Name="MT Flames 6.dds"/>
      </Wheel>
      <Wheel Name="Gobo Wheel 1">
        <Slot Color="0.312730,0.329020,100.000000" MediaFileName="Blank gobo" Name=""/>
        <Slot Color="0.312730,0.329020,100.000000" MediaFileName="MT Crackle" Name="MT Crackle.dds"/>
        <Slot Color="0.312730,0.329020,100.000000" MediaFileName="MT Triangles (small)" Name="MT Triangles (small).dds"/>
        <Slot Color="0.312730,0.329020,100.000000" MediaFileName="MT Tye Dye" Name="MT Tye Dye.dds"/>
        <Slot Color="0.312730,0.329020,100.000000" MediaFileName="MT Globo" Name="MT Globo.dds"/>
        <Slot Color="0.312730,0.329020,100.000000" MediaFileName="MT Worms" Name="MT Worms.dds"/>
        <Slot Color="0.312730,0.329020,100.000000" MediaFileName="MT Bio" Name="MT Bio.dds"/>
        <Slot Color="0.312730,0.329020,100.000000" MediaFileName="MT Leaf Breakup (medium)" Name="MT Leaf Breakup (medium).dds"/>
        <Slot Color="0.312730,0.329020,100.000000" MediaFileName="MT 'les mis' Whirlpool" Name="MT 'les mis' Whirlpool.dds"/>
        <Slot Color="0.312730,0.329020,100.000000" MediaFileName="MT Two Tone" Name="MT Two Tone.dds"/>
      </Wheel>
      <Wheel Name="Color Wheel 1">
        <Slot Color="79.000000,2.000000,207.000000" Name="R385"/>
        <Slot Color="0.000000,166.000000,86.000000" Name="L124"/>
        <Slot Color="255.000000,76.000000,151.000000" Name="L111"/>
        <Slot Color="255.000000,102.000000,19.000000" Name="R21"/>
        <Slot Color="255.000000,210.000000,230.000000" Name="L248"/>
        <Slot Color="204.000000,219.000000,252.000000" Name="MCTC32-41K"/>
        <Slot Color="255.000000,213.000000,156.000000" Name="MCTC55-34K"/>
        <Slot Color="176.000000,2.000000,2.000000" Name="R27"/>
      </Wheel>
      <Wheel Name="Animation Wheel 1">
        <Slot Color="0.312730,0.329020,100.000000" MediaFileName="Martin_Radial_Anim.dds" Name="Martin_Radial_Anim.dds"/>
      </Wheel>
    </Wheels>
    <PhysicalDescriptions>
      <ColorSpace Mode="sRGB"/>
      <Filters/>
      <Emitters/>
      <DMXProfiles/>
      <CRIs/>
      <Connectors/>
      <Properties/>
      <OperatingTemperature High="40.000000" Low="0.000000"/>
      <Weight Value="0.000000"/>
      <LegHeight Value="0.000000"/>
    </PhysicalDescriptions>
    <Models>
      <Model File="Base" Height="0.107950" Length="0.449580" Name="Base" PrimitiveType="Undefined" Width="0.411589"/>
      <Model File="Yoke" Height="0.304042" Length="0.370068" Name="Yoke" PrimitiveType="Undefined" Width="0.157036"/>
      <Model File="Body" Height="0.431733" Length="0.254219" Name="Body" PrimitiveType="Undefined" Width="0.258141"/>
    </Models>
    <Geometries>
      <Axis Model="Base" Name="Base" Position="{1.000000,0.000000,0.000000,0.000000}{0.000000,1.000000,0.000000,-0.022914}{0.000000,0.000000,1.000000,-0.053821}{0,0,0,1}">
        <Axis Model="Yoke" Name="Yoke" Position="{1.000000,0.000000,0.000000,-0.000000}{0.000000,1.000000,0.000000,0.022914}{0.000000,0.000000,1.000000,-0.206393}{0,0,0,1}">
          <Axis Model="Body" Name="Body" Position="{1.000000,0.000000,0.000000,0.000000}{0.000000,1.000000,0.000000,0.000000}{0.000000,0.000000,1.000000,-0.154559}{0,0,0,1}"/>
        </Axis>
      </Axis>
    </Geometries>
    <DMXModes>
      <DMXMode Geometry="Base" Name="DMX Mode">
        <DMXChannels>
          <DMXChannel DMXBreak="1" Default="0/1" Geometry="Base" Highlight="None" Offset="1">
            <LogicalChannel Attribute="Dimmer" DMXChangeTimeLimit="0.000000" Master="None" MibFade="0.000000" Snap="No">
              <ChannelFunction Attribute="Dimmer" DMXFrom="0/1" Name="" OriginalAttribute="" PhysicalFrom="0.000000" PhysicalTo="1.000000" RealAcceleration="0.000000" RealFade="0.000000"/>
            </LogicalChannel>
          </DMXChannel>
        </DMXChannels>
        <Relations/>
        <FTMacros/>
      </DMXMode>
    </DMXModes>
    <Revisions>
      <Revision Date="2021-01-12T18:27:42" Text="Created from Vectorworks with customized user data" UserID="0"/>
    </Revisions>
    <FTPresets/>
    <Protocols/>
  </FixtureType>

</GDTF>
